confplot/__init__.py
confplot/confplot.py
tests/__init__.py
tests/test.py
confplot-0.1.1.dist-info/LICENSE
confplot-0.1.1.dist-info/METADATA
confplot-0.1.1.dist-info/WHEEL
confplot-0.1.1.dist-info/top_level.txt
confplot-0.1.1.dist-info/RECORD
