Metadata-Version: 2.1
Name: confplot
Version: 0.1.1
Summary: Plot a pretty confusion matrix (like Matlab) in python using seaborn and matplotlib
Home-page: https://github.com/fcakyon/confplot
Author: Fatih Cagatay Akyon
License: UNKNOWN
Platform: UNKNOWN
Classifier: Programming Language :: Python :: 3
Classifier: License :: OSI Approved :: MIT License
Classifier: Operating System :: OS Independent
Requires-Python: >=3.6
Requires-Dist: numpy (>=1.16.0)
Requires-Dist: matplotlib (>=3.0.0)
Requires-Dist: scikit-learn (>=0.22.2)
Requires-Dist: pandas (>=1.0.0)
Requires-Dist: seaborn (>=0.10.1)
